MANIFEST.in
setup.py
dautil/__init__.py
dautil/collect.py
dautil/conf.py
dautil/data.py
dautil/db.py
dautil/log.conf
dautil/log_api.py
dautil/nb.py
dautil/options.py
dautil/perf.py
dautil/plotting.py
dautil/report.py
dautil/stats.py
dautil/ts.py
dautil/weather.pckl
dautil/web.py
dautil.egg-info/PKG-INFO
dautil.egg-info/SOURCES.txt
dautil.egg-info/dependency_links.txt
dautil.egg-info/not-zip-safe
dautil.egg-info/requires.txt
dautil.egg-info/top_level.txt