Metadata-Version: 1.0
Name: dautil
Version: 0.0.1a28
Summary: Data analysis utilities
Home-page: https://www.packtpub.com/books/info/authors/ivan-idris
Author: Ivan Idris
Author-email: ivan.idris@gmail.com
License: MIT
Platform: UNKNOWN
